cellects/__init__.py
cellects/__main__.py
cellects/config/__init__.py
cellects/config/all_vars_dict.py
cellects/core/__init__.py
cellects/core/cellects_paths.py
cellects/core/cellects_threads.py
cellects/core/motion_analysis.py
cellects/core/one_image_analysis.py
cellects/core/program_organizer.py
cellects/core/script_based_run.py
cellects/gui/__init__.py
cellects/gui/advanced_parameters.py
cellects/gui/cellects.py
cellects/gui/custom_widgets.py
cellects/gui/first_window.py
cellects/gui/if_several_folders_window.py
cellects/gui/image_analysis_window.py
cellects/gui/required_output.py
cellects/gui/ui_strings.py
cellects/gui/video_analysis_window.py
cellects/icons/__init__.py
cellects/icons/cellects_icon.icns
cellects/icons/cellects_icon.ico
cellects/icons/cellects_icon.png
cellects/image_analysis/__init__.py
cellects/image_analysis/cell_leaving_detection.py
cellects/image_analysis/image_segmentation.py
cellects/image_analysis/morphological_operations.py
cellects/image_analysis/network_functions.py
cellects/image_analysis/one_image_analysis_threads.py
cellects/image_analysis/oscillations_functions.py
cellects/image_analysis/progressively_add_distant_shapes.py
cellects/image_analysis/shape_descriptors.py
cellects/utils/__init__.py
cellects/utils/decorators.py
cellects/utils/formulas.py
cellects/utils/load_display_save.py
cellects/utils/utilitarian.py
cellects-0.3.9.dist-info/LICENSE
cellects-0.3.9.dist-info/METADATA
cellects-0.3.9.dist-info/WHEEL
cellects-0.3.9.dist-info/entry_points.txt
cellects-0.3.9.dist-info/top_level.txt
cellects-0.3.9.dist-info/RECORD
