Metadata-Version: 2.2
Name: cellects
Version: 0.3.9
Summary: Cell Expansion Computer Tracking Software.
Author: Aurèle Boussard
License:                     GNU GENERAL PUBLIC LICENSE
Project-URL: Homepage, https://github.com/Aurele-B/Cellects
Project-URL: Issues, https://github.com/Aurele-B/Cellects/issues
Classifier: Programming Language :: Python :: 3
Classifier: License :: OSI Approved :: GNU General Public License v3 (GPLv3)
Classifier: Operating System :: OS Independent
Requires-Python: <3.14,>=3.11
License-File: LICENSE
Requires-Dist: coloredlogs
Requires-Dist: exif
Requires-Dist: ExifRead
Requires-Dist: numba
Requires-Dist: opencv-python
Requires-Dist: pandas
Requires-Dist: psutil
Requires-Dist: PySide6>=6.5
Requires-Dist: scipy
Requires-Dist: screeninfo
Requires-Dist: numpy>=1.26
Requires-Dist: scikit-image
Requires-Dist: tqdm
Requires-Dist: h5py
Requires-Dist: matplotlib
Requires-Dist: natsort
Provides-Extra: test
Requires-Dist: pytest; extra == "test"
Requires-Dist: pytest-env; extra == "test"
Requires-Dist: pytest-cov; extra == "test"
Provides-Extra: doc
Requires-Dist: mkdocs; extra == "doc"
Requires-Dist: mkdocs-material; extra == "doc"
Requires-Dist: mkdocstrings[python]; extra == "doc"
Requires-Dist: mkdocs-gen-files; extra == "doc"
Requires-Dist: mkdocs-autorefs; extra == "doc"
Requires-Dist: pymdown-extensions; extra == "doc"
Requires-Dist: mkdocs-literate-nav; extra == "doc"
Requires-Dist: mkdocs-section-index; extra == "doc"
Requires-Dist: mkdocs-jupyter; extra == "doc"
